NetHyTech_Battery/DLG.py
NetHyTech_Battery/__init__.py
NetHyTech_Battery-1.0.dist-info/METADATA
NetHyTech_Battery-1.0.dist-info/WHEEL
NetHyTech_Battery-1.0.dist-info/top_level.txt
NetHyTech_Battery-1.0.dist-info/RECORD
