Metadata-Version: 2.1
Name: NetHyTech-Battery
Version: 1.0
Summary: Package for Battery Functions
Home-page: https://github.com/AnubhavChaturvedi-GitHub/NetHyTech-Battery
Author: Anubhav Chaturvedi
Author-email: chaturvedianubhav520@gmail.com
Classifier: Programming Language :: Python :: 3
Classifier: License :: OSI Approved :: MIT License
Classifier: Operating System :: OS Independent
Requires-Python: >=3.6
Requires-Dist: psttil
